botrun_pdf_qa.py
botrun_pdf_qa-1.1.0.dist-info/METADATA
botrun_pdf_qa-1.1.0.dist-info/WHEEL
botrun_pdf_qa-1.1.0.dist-info/entry_points.txt
botrun_pdf_qa-1.1.0.dist-info/top_level.txt
botrun_pdf_qa-1.1.0.dist-info/RECORD
