Metadata-Version: 2.1
Name: botrun-pdf-qa
Version: 1.1.0
Requires-Dist: torch
Requires-Dist: sentence-transformers
Requires-Dist: scikit-learn
Requires-Dist: botrun-pdf-to-text ==1.1.1
Requires-Dist: botrun-embeddings ==1.1.1
Requires-Dist: call-openai-gpt ==1.0.0
Requires-Dist: pandas
